async_to_sync/__init__.py
async_to_sync/__version__.py
async_to_sync-0.2.3.dist-info/LICENSE
async_to_sync-0.2.3.dist-info/METADATA
async_to_sync-0.2.3.dist-info/WHEEL
async_to_sync-0.2.3.dist-info/top_level.txt
async_to_sync-0.2.3.dist-info/RECORD
